setup.py
recv/__init__.py
recv/__main__.py
recv.egg-info/PKG-INFO
recv.egg-info/SOURCES.txt
recv.egg-info/dependency_links.txt
recv.egg-info/top_level.txt