Metadata-Version: 1.0
Name: recv
Version: 0.2.0
Summary: Recv file
Home-page: UNKNOWN
Author: UNKNOWN
Author-email: UNKNOWN
License: UNKNOWN
Platform: UNKNOWN
